odoo/addons/l10n_it_mis_reports_pl_bs/README.rst
odoo/addons/l10n_it_mis_reports_pl_bs/__init__.py
odoo/addons/l10n_it_mis_reports_pl_bs/__manifest__.py
odoo/addons/l10n_it_mis_reports_pl_bs/data/mis_report_bs.xml
odoo/addons/l10n_it_mis_reports_pl_bs/data/mis_report_pl.xml
odoo/addons/l10n_it_mis_reports_pl_bs/data/mis_report_styles.xml
odoo/addons/l10n_it_mis_reports_pl_bs/i18n/it.po
odoo/addons/l10n_it_mis_reports_pl_bs/i18n/l10n_it_mis_reports_pl_bs.pot
odoo/addons/l10n_it_mis_reports_pl_bs/readme/CONFIGURE.rst
odoo/addons/l10n_it_mis_reports_pl_bs/readme/CONTRIBUTORS.rst
odoo/addons/l10n_it_mis_reports_pl_bs/readme/DESCRIPTION.rst
odoo/addons/l10n_it_mis_reports_pl_bs/readme/INSTALL.rst
odoo/addons/l10n_it_mis_reports_pl_bs/readme/USAGE.rst
odoo/addons/l10n_it_mis_reports_pl_bs/static/description/icon.png
odoo/addons/l10n_it_mis_reports_pl_bs/static/description/index.html
odoo12_addon_l10n_it_mis_reports_pl_bs-12.0.1.0.1.dist-info/METADATA
odoo12_addon_l10n_it_mis_reports_pl_bs-12.0.1.0.1.dist-info/WHEEL
odoo12_addon_l10n_it_mis_reports_pl_bs-12.0.1.0.1.dist-info/top_level.txt
odoo12_addon_l10n_it_mis_reports_pl_bs-12.0.1.0.1.dist-info/RECORD
