Metadata-Version: 2.1
Name: odoo12-addon-l10n-it-mis-reports-pl-bs
Version: 12.0.1.0.1
Summary: Modelli "MIS Builder" per il conto economico e lo stato patrimoniale
Home-page: https://github.com/OCA/l10n-italy
Author: Dinamiche Aziendali srl,Odoo Community Association (OCA)
Author-email: support@odoo-community.org
License: AGPL-3
Platform: UNKNOWN
Classifier: Programming Language :: Python
Classifier: Framework :: Odoo
Classifier: License :: OSI Approved :: GNU Affero General Public License v3
Requires-Python: >=3.5
Requires-Dist: odoo12-addon-mis-builder
Requires-Dist: odoo (<12.1dev,>=12.0a)
